{"commitInfo":{"timestamp":1784401086788,"operation":"WRITE","operationParameters":{"mode":"Overwrite","partitionBy":"[]"},"readVersion":2,"isolationLevel":"Serializable","isBlindAppend":false,"operationMetrics":{"numFiles":"1","numOutputRows":"74","numOutputBytes":"2323"},"engineInfo":"Apache-Spark/3.5.8 Delta-Lake/3.2.1","txnId":"8bf0a2e9-3778-49d9-ae51-f452a660ea7d"}}
{"add":{"path":"part-00000-993f4c44-3d0c-4546-ac41-c842537bf564-c000.snappy.parquet","partitionValues":{},"size":2323,"modificationTime":1784401086555,"dataChange":true,"stats":"{\"numRecords\":74,\"minValues\":{\"year\":2022,\"month\":1,\"city\":\"In-store\",\"revenue\":12130.0,\"orders\":99},\"maxValues\":{\"year\":2025,\"month\":12,\"city\":\"Online\",\"revenue\":27994.5,\"orders\":216},\"nullCount\":{\"year\":0,\"month\":0,\"city\":0,\"revenue\":0,\"orders\":0}}"}}
{"remove":{"path":"part-00000-e0bea955-51df-4a1a-890b-3f9378a5c1ed-c000.snappy.parquet","deletionTimestamp":1784401086787,"dataChange":true,"extendedFileMetadata":true,"partitionValues":{},"size":2323}}
